namethis/__init__.py
namethis/namethis.py
namethis/data/resourceDefinition.json
namethis/tests/__init__.py
namethis/tests/test_namethis.py
namethis-0.4.0.dist-info/METADATA
namethis-0.4.0.dist-info/WHEEL
namethis-0.4.0.dist-info/licenses/LICENSE
namethis-0.4.0.dist-info/RECORD
