Metadata-Version: 2.3
Name: namethis
Version: 0.4.0
Summary: Returns a set of AzureRM resoruce names
Project-URL: Homepage, https://dev.azure.com/dev-the-office/namethis
Project-URL: Repository, https://dev.azure.com/dev-the-office/_git/namethis
Project-URL: Documentation, https://dev.azure.com/dev-the-office/_git/namethis/README.md
Author-email: Tomas Maggio <tomas-pypi@maggio.nz>
License: MIT License
License-File: LICENSE
Keywords: azure,naming,resource
Classifier: License :: OSI Approved :: MIT License
Classifier: Operating System :: OS Independent
Classifier: Programming Language :: Python :: 3
Requires-Python: >=3.9
